mmdt_tokenizer/__init__.py
mmdt_tokenizer/core.py
mmdt_tokenizer/preprocessing/__init__.py
mmdt_tokenizer/preprocessing/cleaner.py
mmdt_tokenizer/preprocessing/normalizer.py
mmdt_tokenizer/preprocessing/preprocess.py
mmdt_tokenizer/preprocessing/protector.py
mmdt_tokenizer/rule_segmenter/__init__.py
mmdt_tokenizer/rule_segmenter/cleanner.py
mmdt_tokenizer/rule_segmenter/collapse.py
mmdt_tokenizer/rule_segmenter/config.py
mmdt_tokenizer/rule_segmenter/engine.py
mmdt_tokenizer/rule_segmenter/lexicon.py
mmdt_tokenizer/rule_segmenter/lexicons.json
mmdt_tokenizer/rule_segmenter/merge_ops.py
mmdt_tokenizer/rule_segmenter/scanner.py
mmdt_tokenizer/rule_segmenter/types.py
mmdt_tokenizer/tokenizer/__init__.py
mmdt_tokenizer/tokenizer/syllable_tokenizer.py
mmdt_tokenizer/tokenizer/word_tokenizer.py
mmdt_tokenizer/utils/__init__.py
mmdt_tokenizer/utils/config.py
mmdt_tokenizer/utils/csv_utils.py
mmdt_tokenizer/utils/data_utils.py
mmdt_tokenizer/utils/patterns.py
mmdt_tokenizer-0.1.3.dist-info/METADATA
mmdt_tokenizer-0.1.3.dist-info/WHEEL
mmdt_tokenizer-0.1.3.dist-info/licenses/LICENSE
mmdt_tokenizer-0.1.3.dist-info/RECORD
