Metadata-Version: 2.4
Name: mmdt-tokenizer
Version: 0.1.3
Summary: Myanmar Text Segmenter
Author: MMDT
License: MIT
License-File: LICENSE
Requires-Python: >=3.10
Requires-Dist: numpy
Requires-Dist: pandas
Provides-Extra: dev
Requires-Dist: black; extra == 'dev'
Requires-Dist: jupyter; extra == 'dev'
Requires-Dist: pytest; extra == 'dev'
